[{"person":{"name":"Nicka","surname":"Garcia","birthday":"2002-11-22T00:00:00"},"level_to_obtain":0,"list_passed_exams":[{"title":"Algebra","date":"2021-02-14T00:00:00","grade":40},{"title":"Biology","date":"2021-10-17T00:00:00","grade":75},{"title":"Drawing","date":"2021-01-22T00:00:00","grade":34},{"title":"Chemistry","date":"2021-10-11T00:00:00","grade":34}]},{"person":{"name":"Jessy","surname":"Lopez","birthday":"2002-04-13T00:00:00"},"level_to_obtain":2,"list_passed_exams":[{"title":"Algebra","date":"2021-09-16T00:00:00","grade":96},{"title":"Biology","date":"2021-05-03T00:00:00","grade":59},{"title":"Drawing","date":"2021-11-15T00:00:00","grade":65}]},{"person":{"name":"Oleg","surname":"Lopez","birthday":"2002-11-24T00:00:00"},"level_to_obtain":0,"list_passed_exams":[{"title":"Algebra","date":"2021-02-09T00:00:00","grade":89}]},{"person":{"name":"Oleg","surname":"Jones","birthday":"2002-04-13T00:00:00"},"level_to_obtain":2,"list_passed_exams":[{"title":"Algebra","date":"2021-10-17T00:00:00","grade":52}]},{"person":{"name":"Pitter","surname":"Jones","birthday":"2002-01-09T00:00:00"},"level_to_obtain":0,"list_passed_exams":[{"title":"Algebra","date":"2021-08-07T00:00:00","grade":53},{"title":"Biology","date":"2021-03-18T00:00:00","grade":98},{"title":"Drawing","date":"2021-10-13T00:00:00","grade":37}]},{"person":{"name":"Ivan","surname":"Miller","birthday":"2002-03-11T00:00:00"},"level_to_obtain":1,"list_passed_exams":[{"title":"Algebra","date":"2021-10-19T00:00:00","grade":62}]},{"person":{"name":"Petr","surname":"Parker","birthday":"2002-01-01T00:00:00"},"level_to_obtain":0,"list_passed_exams":[{"title":"Algebra","date":"2021-06-02T00:00:00","grade":29}]}]